pyfrontkit/__init__.py
pyfrontkit/block.py
pyfrontkit/content.py
pyfrontkit/css_register.py
pyfrontkit/dom.py
pyfrontkit/html_doc.py
pyfrontkit/style_manager.py
pyfrontkit/tags.py
pyfrontkit/void_element.py
pyfrontkit/css/__init__.py
pyfrontkit/css/fonts.py
pyfrontkit/css/create_color/__init__.py
pyfrontkit/css/create_color/create_colors.py
pyfrontkit/css/create_color/palettes.py
pyfrontkit/css/create_color/colors_templates/__init__.py
pyfrontkit/css/create_color/colors_templates/asimetric_template.py
pyfrontkit/css/create_color/colors_templates/classic_reverse_template.py
pyfrontkit/css/create_color/colors_templates/classic_template.py
pyfrontkit/css/create_color/colors_templates/dark_reverse_template.py
pyfrontkit/css/create_color/colors_templates/darkness_template.py
pyfrontkit/css/create_color/colors_templates/enfasis_main_template.py
pyfrontkit/css/create_color/colors_templates/mono_accent_template.py
pyfrontkit/css/create_color/colors_templates/mono_template.py
pyfrontkit/css/create_color/colors_templates/simple_template.py
pyfrontkit/css/create_color/colors_templates/soft_template.py
pyfrontkit/css/create_color/colors_templates/total_template.py
pyfrontkit/css/create_color/colors_templates/total_v2_template.py
pyfrontkit-1.1.21.dist-info/METADATA
pyfrontkit-1.1.21.dist-info/WHEEL
pyfrontkit-1.1.21.dist-info/top_level.txt
pyfrontkit-1.1.21.dist-info/RECORD
