Metadata-Version: 2.4
Name: pyfrontkit
Version: 1.1.21
Summary: A Python tool to generate HTML and CSS with programmable syntax.
Author-email: Eduardo Antonio Ferrera Rodríguez <enzoferrera.23@gmail.com>
License: MIT
Project-URL: Homepage, https://github.com/Edybrown/pyfrontkit
Project-URL: Source, https://github.com/Edybrown/pyfrontkit
Project-URL: Issues, https://github.com/Edybrown/pyfrontkit/issues
Keywords: html,css,python,frontend,mlops,data app
Classifier: Programming Language :: Python :: 3
Classifier: License :: OSI Approved :: MIT License
Classifier: Operating System :: OS Independent
Requires-Python: >=3.8
